aliyun/semconv/__init__.py
aliyun/semconv/version.py
aliyun/semconv/logger/__init__.py
aliyun/semconv/metrics/__init__.py
aliyun/semconv/trace/__init__.py
aliyun_semantic_conventions-1.2.0.dist-info/METADATA
aliyun_semantic_conventions-1.2.0.dist-info/WHEEL
aliyun_semantic_conventions-1.2.0.dist-info/RECORD
